scrapegraphai/__init__.py
scrapegraphai/builders/__init__.py
scrapegraphai/builders/graph_builder.py
scrapegraphai/docloaders/__init__.py
scrapegraphai/docloaders/browser_base.py
scrapegraphai/docloaders/chromium.py
scrapegraphai/docloaders/scrape_do.py
scrapegraphai/graphs/__init__.py
scrapegraphai/graphs/abstract_graph.py
scrapegraphai/graphs/base_graph.py
scrapegraphai/graphs/code_generator_graph.py
scrapegraphai/graphs/csv_scraper_graph.py
scrapegraphai/graphs/csv_scraper_multi_graph.py
scrapegraphai/graphs/depth_search_graph.py
scrapegraphai/graphs/document_scraper_graph.py
scrapegraphai/graphs/document_scraper_multi_graph.py
scrapegraphai/graphs/json_scraper_graph.py
scrapegraphai/graphs/json_scraper_multi_graph.py
scrapegraphai/graphs/omni_scraper_graph.py
scrapegraphai/graphs/omni_search_graph.py
scrapegraphai/graphs/screenshot_scraper_graph.py
scrapegraphai/graphs/script_creator_graph.py
scrapegraphai/graphs/script_creator_multi_graph.py
scrapegraphai/graphs/search_graph.py
scrapegraphai/graphs/search_link_graph.py
scrapegraphai/graphs/smart_scraper_graph.py
scrapegraphai/graphs/smart_scraper_multi_concat_graph.py
scrapegraphai/graphs/smart_scraper_multi_graph.py
scrapegraphai/graphs/speech_graph.py
scrapegraphai/graphs/xml_scraper_graph.py
scrapegraphai/graphs/xml_scraper_multi_graph.py
scrapegraphai/helpers/__init__.py
scrapegraphai/helpers/default_filters.py
scrapegraphai/helpers/models_tokens.py
scrapegraphai/helpers/nodes_metadata.py
scrapegraphai/helpers/robots.py
scrapegraphai/helpers/schemas.py
scrapegraphai/integrations/__init__.py
scrapegraphai/integrations/burr_bridge.py
scrapegraphai/integrations/indexify_node.py
scrapegraphai/models/__init__.py
scrapegraphai/models/deepseek.py
scrapegraphai/models/oneapi.py
scrapegraphai/models/openai_itt.py
scrapegraphai/models/openai_tts.py
scrapegraphai/nodes/__init__.py
scrapegraphai/nodes/base_node.py
scrapegraphai/nodes/concat_answers_node.py
scrapegraphai/nodes/conditional_node.py
auk_scrapegraphai-1.26.0b19.dist-info/METADATA
auk_scrapegraphai-1.26.0b19.dist-info/WHEEL
auk_scrapegraphai-1.26.0b19.dist-info/licenses/LICENSE
auk_scrapegraphai-1.26.0b19.dist-info/RECORD
