Metadata-Version: 2.3
Name: auk-scrapegraphai
Version: 1.26.0b19
Summary: A web scraping library based on LangChain which uses LLM and direct graph logic to create scraping pipelines.
Author-email: Aziz Ullah Khan <azizullah444@gmail.com>, Marco Vinciguerra <mvincig11@gmail.com>, Marco Perini <perinim.98@gmail.com>, Lorenzo Padoan <lorenzo.padoan977@gmail.com>
License-Expression: MIT
License-File: LICENSE
Keywords: ai,artificial intelligence,gpt,graph,langchain,llm,machine learning,natural language processing,nlp,openai,rag,scrapegraph,scrapegraphai,scraping,web scraping,web scraping library,web scraping tool,webscraping
Classifier: Intended Audience :: Developers
Classifier: Operating System :: OS Independent
Classifier: Programming Language :: Python :: 3
Classifier: Topic :: Software Development :: Libraries :: Python Modules
Requires-Python: <4.0,>=3.10
Requires-Dist: beautifulsoup4>=4.12.3
Requires-Dist: fastembed>=0.3.6
Requires-Dist: free-proxy>=1.1.1
Requires-Dist: googlesearch-python>=1.2.5
Requires-Dist: html2text>=2024.2.26
Requires-Dist: langchain-aws>=0.1.3
Requires-Dist: langchain-community>=0.2.9
Requires-Dist: langchain-google-genai>=1.0.7
Requires-Dist: langchain-mistralai>=0.1.12
Requires-Dist: langchain-ollama>=0.1.3
Requires-Dist: langchain-openai>=0.1.22
Requires-Dist: langchain>=0.3.0
Requires-Dist: minify-html>=0.15.0
Requires-Dist: mistral-common>=1.4.0
Requires-Dist: pandas>=2.2.2
Requires-Dist: playwright>=1.43.0
Requires-Dist: python-dotenv>=1.0.1
Requires-Dist: qdrant-client>=1.11.3
Requires-Dist: semchunk>=2.2.0
Requires-Dist: simpleeval>=0.9.13
Requires-Dist: tiktoken>=0.7
Requires-Dist: tqdm>=4.66.4
Requires-Dist: transformers>=4.44.2
Requires-Dist: undetected-playwright>=0.3.0
Provides-Extra: burr
Requires-Dist: burr[start]==0.22.1; extra == 'burr'
Provides-Extra: docs
Requires-Dist: furo==2024.5.6; extra == 'docs'
Requires-Dist: sphinx==6.0; extra == 'docs'
Provides-Extra: more-browser-options
Requires-Dist: browserbase>=0.3.0; extra == 'more-browser-options'
Provides-Extra: more-semantic-options
Requires-Dist: graphviz>=0.20.3; extra == 'more-semantic-options'
Provides-Extra: other-language-models
Requires-Dist: langchain-anthropic>=0.1.11; extra == 'other-language-models'
Requires-Dist: langchain-fireworks>=0.1.3; extra == 'other-language-models'
Requires-Dist: langchain-google-vertexai>=1.0.7; extra == 'other-language-models'
Requires-Dist: langchain-groq>=0.1.3; extra == 'other-language-models'
Requires-Dist: langchain-huggingface>=0.0.3; extra == 'other-language-models'
Requires-Dist: langchain-nvidia-ai-endpoints>=0.1.6; extra == 'other-language-models'
Requires-Dist: langchain-together>=1.2.9; extra == 'other-language-models'
Provides-Extra: screenshot-scraper
Requires-Dist: ipywidgets>=8.1.0; extra == 'screenshot-scraper'
Requires-Dist: matplotlib>=3.7.2; extra == 'screenshot-scraper'
Requires-Dist: pillow>=10.4.0; extra == 'screenshot-scraper'
Requires-Dist: surya-ocr>=0.5.0; extra == 'screenshot-scraper'
